brian2lava/__init__.py
brian2lava/codegen/codeobject.py
brian2lava/codegen/lava_generator.py
brian2lava/codegen/templater.py
brian2lava/codegen/templates/activation_processing.py_
brian2lava/codegen/templates/common_group.py_
brian2lava/codegen/templates/group_get_indices.py_
brian2lava/codegen/templates/group_variable_get.py_
brian2lava/codegen/templates/group_variable_get_conditional.py_
brian2lava/codegen/templates/group_variable_set.py_
brian2lava/codegen/templates/group_variable_set_conditional.py_
brian2lava/codegen/templates/ratemonitor.py_
brian2lava/codegen/templates/reset.py_
brian2lava/codegen/templates/spatialstateupdate.py_
brian2lava/codegen/templates/spikegenerator.py_
brian2lava/codegen/templates/spikemonitor.py_
brian2lava/codegen/templates/statemonitor.py_
brian2lava/codegen/templates/stateupdate.py_
brian2lava/codegen/templates/summed_variable.py_
brian2lava/codegen/templates/synapses.py_
brian2lava/codegen/templates/synapses_create_array.py_
brian2lava/codegen/templates/synapses_create_generator.py_
brian2lava/codegen/templates/synapses_push_spikes.py_
brian2lava/codegen/templates/synapses_transmit.py_
brian2lava/codegen/templates/threshold.py_
brian2lava/device/__init__.py
brian2lava/device/activate.py
brian2lava/device/arrays.py
brian2lava/device/build.py
brian2lava/device/codeobject.py
brian2lava/device/run.py
brian2lava/device/synapses.py
brian2lava/device/variables.py
brian2lava/device/writer.py
brian2lava/templates/process.py.j2
brian2lava/templates/process_model.py.j2
brian2lava/writer/py.py
brian2lava-1.0.0a3.dist-info/LICENSE
brian2lava-1.0.0a3.dist-info/METADATA
brian2lava-1.0.0a3.dist-info/WHEEL
brian2lava-1.0.0a3.dist-info/top_level.txt
brian2lava-1.0.0a3.dist-info/RECORD
