Metadata-Version: 2.1
Name: brian2lava
Version: 1.0.0a3
Summary: An open source Brian2 interface for the neuromorphic computing framework Lava
Home-page: https://gitlab.com/tetzlab/brian2lava
Author: Carlo Michaelis, Francesco Negri, Winfried Oed, Jannik Luboeinski, Andrew Lehr, Tristan Stöber
Author-email: carlo.michaelis@gmail.com
License: MIT
Platform: UNKNOWN
Requires-Python: >3.8
Requires-Dist: brian2 (>=2.5.1)
Requires-Dist: jinja2 (>=2.7)
Requires-Dist: lava-nc (>=0.7.0)
Requires-Dist: markupsafe (==2.0.1)
Requires-Dist: matplotlib
Requires-Dist: numpy
Requires-Dist: pytest
Requires-Dist: regex (>=2022.10.31)
Requires-Dist: scipy
